ecnunetwork/__init__.py
ecnunetwork/commandline.py
ecnunetwork/test/__init__.py
ecnunetwork/test/test_ecnunetwork.py
ecnunetwork-1.1.6.dist-info/METADATA
ecnunetwork-1.1.6.dist-info/WHEEL
ecnunetwork-1.1.6.dist-info/entry_points.txt
ecnunetwork-1.1.6.dist-info/top_level.txt
ecnunetwork-1.1.6.dist-info/zip-safe
ecnunetwork-1.1.6.dist-info/RECORD
