Metadata-Version: 2.1
Name: ecnunetwork
Version: 1.1.6
Summary: A script to connect to Internet at East China Normal University (ECNU).
Home-page: https://github.com/njzjz/ecnunetwork
Author: Jinzhe Zeng
Author-email: jzzeng@stu.ecnu.edu.cn
License: UNKNOWN
Keywords: ecnu
Platform: UNKNOWN
Classifier: Natural Language :: English
Classifier: Operating System :: POSIX :: Linux
Classifier: Operating System :: Microsoft :: Windows
Classifier: Programming Language :: Python :: 2.7
Classifier: Programming Language :: Python :: 3.5
Classifier: Programming Language :: Python :: 3.6
Classifier: Programming Language :: Python :: 3.7
Classifier: Topic :: Software Development :: Libraries :: Python Modules
Classifier: Topic :: Software Development :: Version Control :: Git
Requires-Dist: requests
Requires-Dist: six
Provides-Extra: test
Requires-Dist: pytest-sugar ; extra == 'test'
Requires-Dist: pytest-cov ; extra == 'test'
Requires-Dist: pytest-localserver ; extra == 'test'
